spark_dash/__init__.py
spark_dash/cmd.py
spark_dash/main.py
spark_dash/utils.py
spark_dash/conf/config.ini
spark_dash/conf/docker-compose.yml
spark_dash/pages/scale_log.py
spark_dash/pages/usage_log.py
spark_dash-0.3.3.dist-info/METADATA
spark_dash-0.3.3.dist-info/WHEEL
spark_dash-0.3.3.dist-info/entry_points.txt
spark_dash-0.3.3.dist-info/top_level.txt
spark_dash-0.3.3.dist-info/RECORD
