Metadata-Version: 2.1
Name: spark-dash
Version: 0.3.3
Summary: Spark-worker의 CPU 사용량을 확인하며 Scale in/out을 할 수 있는 dashboard를 제공합니다.
Author-email: Mingk42 <xoals123456t@gmail.com>
License: MIT
Requires-Python: >=3.11
Requires-Dist: streamlit>=1.40.1
Requires-Dist: schedule>=1.2.2
Requires-Dist: tz-kst>=0.5.3
Requires-Dist: matplotlib>=3.9.2
